hapne/__init__.py
hapne/fit.py
hapne/ibd.py
hapne/ld.py
hapne/output.py
hapne/utils.py
hapne/backend/DemographicHistory.py
hapne/backend/DemographicHistory2StatsModelAdapter.py
hapne/backend/HapNe.py
hapne/backend/IO.py
hapne/backend/StatsModel.py
hapne/backend/__init__.py
hapne/convert/__init__.py
hapne/convert/tools.py
hapne/convert/mathii_scripts/__init__.py
hapne/convert/mathii_scripts/py3Eigenstrat.py
hapne/files/regions_grch37.txt
hapne/files/regions_grch38.txt
hapne-1.20240807.dist-info/LICENSE
hapne-1.20240807.dist-info/METADATA
hapne-1.20240807.dist-info/WHEEL
hapne-1.20240807.dist-info/top_level.txt
hapne-1.20240807.dist-info/RECORD
